hestia_earth/extend_bibliography/__init__.py
hestia_earth/extend_bibliography/log.py
hestia_earth/extend_bibliography/utils.py
hestia_earth/extend_bibliography/version.py
hestia_earth/extend_bibliography/bibliography_apis/__init__.py
hestia_earth/extend_bibliography/bibliography_apis/crossref.py
hestia_earth/extend_bibliography/bibliography_apis/mendeley.py
hestia_earth/extend_bibliography/bibliography_apis/unpaywall.py
hestia_earth/extend_bibliography/bibliography_apis/utils.py
hestia_earth/extend_bibliography/bibliography_apis/wos.py
hestia_earth/extend_bibliography/bibliography_apis/mendeley_api/__init__.py
hestia_earth/extend_bibliography/bibliography_apis/mendeley_api/client.py
hestia_earth/extend_bibliography/bibliography_apis/mendeley_sdk/__init__.py
hestia_earth/extend_bibliography/bibliography_apis/mendeley_sdk/client.py
hestia_earth/extend_bibliography/bibliography_apis/mendeley_sdk/session.py
hestia_earth/extend_bibliography/bibliography_apis/wos_rest/__init__.py
hestia_earth/extend_bibliography/bibliography_apis/wos_rest/client.py
hestia_earth_extend_bibliography-0.6.0.dist-info/licenses/LICENSE
hestia_earth_extend_bibliography-0.6.0.dist-info/METADATA
hestia_earth_extend_bibliography-0.6.0.dist-info/WHEEL
hestia_earth_extend_bibliography-0.6.0.dist-info/dependency_links.txt
hestia_earth_extend_bibliography-0.6.0.dist-info/top_level.txt
hestia_earth_extend_bibliography-0.6.0.dist-info/RECORD
