Metadata-Version: 2.4
Name: hestia_earth_extend_bibliography
Version: 0.6.0
Summary: Hestia library to extend Bibliography Nodes with different APIs
Home-page: https://gitlab.com/hestia-earth/hestia-data-validation
Author: Guillaume Royer
Author-email: guillaumeroyer.mail@gmail.com
License: MIT
Keywords: hestia,mendeley
Requires-Python: >=3.12
License-File: LICENSE
Requires-Dist: hestia-earth-schema>=35.0.1
Requires-Dist: python-Levenshtein
Requires-Dist: habanero
Requires-Dist: wos
Requires-Dist: xmltodict
Requires-Dist: mendeley
Dynamic: author
Dynamic: author-email
Dynamic: description
Dynamic: description-content-type
Dynamic: home-page
Dynamic: keywords
Dynamic: license
Dynamic: license-file
Dynamic: requires-dist
Dynamic: requires-python
Dynamic: summary
